ferramentas/DFA.py
ferramentas/__init__.py
analise_rasa_plots-1.0.0.dist-info/METADATA
analise_rasa_plots-1.0.0.dist-info/WHEEL
analise_rasa_plots-1.0.0.dist-info/top_level.txt
analise_rasa_plots-1.0.0.dist-info/RECORD
