Metadata-Version: 2.1
Name: analise-rasa-plots
Version: 1.0.0
Summary: create boring and fast plots
Author: AlcimarMT
Author-email: alcimartri1998@gmail.com
License: UNKNOWN
Platform: UNKNOWN
Requires-Python: >=3.5
Requires-Dist: pandas
Requires-Dist: matplotlib
Requires-Dist: numpy
Requires-Dist: seaborn
Requires-Dist: sklearn
